gpupixelpy/__init__.py
gpupixelpy/gpupixel.py
gpupixelpy/lib/windows/blusher.png
gpupixelpy/lib/windows/demo.png
gpupixelpy/lib/windows/face_pc[1.0.0].vnnmodel
gpupixelpy/lib/windows/libgpupixel.dll
gpupixelpy/lib/windows/libgpupixel_pywrapper.dll
gpupixelpy/lib/windows/lookup_custom.png
gpupixelpy/lib/windows/lookup_gray.png
gpupixelpy/lib/windows/lookup_light.png
gpupixelpy/lib/windows/lookup_origin.png
gpupixelpy/lib/windows/lookup_skin.png
gpupixelpy/lib/windows/mouth.png
gpupixelpy/lib/windows/vnn_core.dll
gpupixelpy/lib/windows/vnn_face.dll
gpupixelpy/lib/windows/vnn_kit.dll
gpupixelpy-0.1.0.dist-info/METADATA
gpupixelpy-0.1.0.dist-info/WHEEL
gpupixelpy-0.1.0.dist-info/RECORD
