Metadata-Version: 2.3
Name: gpupixelpy
Version: 0.1.0
Summary: gpupixel python wrapper
Author: angleyanalbedo
Author-email: 100198247+angleyanalbedo@users.noreply.github.com
Requires-Python: >=3.7
Classifier: Programming Language :: Python :: 3
Classifier: Programming Language :: Python :: 3.7
Classifier: Programming Language :: Python :: 3.8
Classifier: Programming Language :: Python :: 3.9
Classifier: Programming Language :: Python :: 3.10
Classifier: Programming Language :: Python :: 3.11
Classifier: Programming Language :: Python :: 3.12
Classifier: Programming Language :: Python :: 3.13
